requestmodel/__init__.py
requestmodel/adapters/__init__.py
requestmodel/adapters/base.py
requestmodel/adapters/httpx.py
requestmodel/adapters/requests.py
requestmodel/fastapi.py
requestmodel/model.py
requestmodel/params.py
requestmodel/py.typed
requestmodel/typing.py
requestmodel/utils.py
requestmodel-0.7.0.dist-info/LICENSE
requestmodel-0.7.0.dist-info/METADATA
requestmodel-0.7.0.dist-info/WHEEL
requestmodel-0.7.0.dist-info/RECORD
